{
    "fluentMethods": true,
    "relationships": [
        {
            "relationshipType": "one-to-many",
            "relationshipName": "cliente",
            "otherEntityName": "cliente",
            "otherEntityRelationshipName": "empresa"
        },
        {
            "relationshipType": "many-to-one",
            "relationshipName": "user",
            "otherEntityName": "user",
            "otherEntityField": "email"
        }
    ],
    "fields": [
        {
            "fieldName": "nombre",
            "fieldType": "String",
            "fieldValidateRules": [
                "required"
            ]
        },
        {
            "fieldName": "domicilio",
            "fieldType": "String",
            "fieldValidateRules": [
                "required"
            ]
        },
        {
            "fieldName": "telefono",
            "fieldType": "String",
            "fieldValidateRules": [
                "required"
            ]
        },
        {
            "fieldName": "categoria",
            "fieldType": "String",
            "fieldValidateRules": [
                "required"
            ]
        }
    ],
    "changelogDate": "20170604152013",
    "entityTableName": "empresa",
    "dto": "mapstruct",
    "pagination": "pager",
    "service": "serviceImpl"
}